{
  "id": "CA1305",
  "language": "csharp",
  "tool": "Microsoft.CodeAnalysis.NetAnalyzers",
  "toolRuleId": "CA1305",
  "title": "Specify IFormatProvider",
  "description": "A method or constructor calls one or more members that have overloads that accept a System.IFormatProvider parameter, and the method or constructor does not call the overload that takes the IFormatProvider parameter. When a System.Globalization.CultureInfo or IFormatProvider object is not supplied, the default value that is supplied by the overloaded member might not have the effect that you want in all locales. If the result will be based on the input from/output displayed to the user, specify 'CultureInfo.CurrentCulture' as the 'IFormatProvider'. Otherwise, if the result will be stored and accessed by software, such as when it is loaded from disk/database and when it is persisted to disk/database, specify 'CultureInfo.InvariantCulture'.",
  "category": "Globalization",
  "defaultSeverity": "none",
  "docs": "https://learn.microsoft.com/dotnet/fundamentals/code-analysis/quality-rules/ca1305"
}
