{
  "id": "CA1860",
  "language": "csharp",
  "tool": "Microsoft.CodeAnalysis.NetAnalyzers",
  "toolRuleId": "CA1860",
  "title": "Avoid using 'Enumerable.Any()' extension method",
  "description": "Prefer using 'IsEmpty', 'Count' or 'Length' properties whichever available, rather than calling 'Enumerable.Any()'. The intent is clearer and it is more performant than using 'Enumerable.Any()' extension method.",
  "category": "Performance",
  "defaultSeverity": "info",
  "docs": "https://learn.microsoft.com/dotnet/fundamentals/code-analysis/quality-rules/ca1860"
}
