{
  "id": "CA2217",
  "language": "csharp",
  "tool": "Microsoft.CodeAnalysis.NetAnalyzers",
  "toolRuleId": "CA2217",
  "title": "Do not mark enums with FlagsAttribute",
  "description": "An externally visible enumeration is marked by using FlagsAttribute, and it has one or more values that are not powers of two or a combination of the other defined values on the enumeration.",
  "category": "Usage",
  "defaultSeverity": "warning",
  "docs": "https://learn.microsoft.com/dotnet/fundamentals/code-analysis/quality-rules/ca2217"
}
