{
  "id": "CA3061",
  "language": "csharp",
  "tool": "Microsoft.CodeAnalysis.NetAnalyzers",
  "toolRuleId": "CA3061",
  "title": "Do Not Add Schema By URL",
  "description": "This overload of XmlSchemaCollection.Add method internally enables DTD processing on the XML reader instance used, and uses UrlResolver for resolving external XML entities. The outcome is information disclosure. Content from file system or network shares for the machine processing the XML can be exposed to attacker. In addition, an attacker can use this as a DoS vector.",
  "category": "Security",
  "defaultSeverity": "none",
  "docs": "https://learn.microsoft.com/dotnet/fundamentals/code-analysis/quality-rules/ca3061"
}
