{
  "id": "CA5359",
  "language": "csharp",
  "tool": "Microsoft.CodeAnalysis.NetAnalyzers",
  "toolRuleId": "CA5359",
  "title": "Do Not Disable Certificate Validation",
  "description": "A certificate can help authenticate the identity of the server. Clients should validate the server certificate to ensure requests are sent to the intended server. If the ServerCertificateValidationCallback always returns 'true', any certificate will pass validation.",
  "category": "Security",
  "defaultSeverity": "none",
  "docs": "https://learn.microsoft.com/dotnet/fundamentals/code-analysis/quality-rules/ca5359"
}
